{"nodes": [{"id": "marketplace_contract", "label": "marketplace.contract.ts", "file_type": "code", "source_file": "c:\\Users\\minhmice\\Documents\\projects\\relique.co\\src\\lib\\domain\\contracts\\marketplace.contract.ts", "source_location": "L1"}], "edges": [{"source": "marketplace_contract", "target": "result", "relation": "imports_from", "confidence": "EXTRACTED", "source_file": "c:\\Users\\minhmice\\Documents\\projects\\relique.co\\src\\lib\\domain\\contracts\\marketplace.contract.ts", "source_location": "L1", "weight": 1.0}, {"source": "marketplace_contract", "target": "errors", "relation": "imports_from", "confidence": "EXTRACTED", "source_file": "c:\\Users\\minhmice\\Documents\\projects\\relique.co\\src\\lib\\domain\\contracts\\marketplace.contract.ts", "source_location": "L2", "weight": 1.0}, {"source": "marketplace_contract", "target": "marketplace", "relation": "imports_from", "confidence": "EXTRACTED", "source_file": "c:\\Users\\minhmice\\Documents\\projects\\relique.co\\src\\lib\\domain\\contracts\\marketplace.contract.ts", "source_location": "L3", "weight": 1.0}]}