{"nodes": [{"id": "partner_strip", "label": "partner-strip.tsx", "file_type": "code", "source_file": "c:\\Users\\minhmice\\Documents\\projects\\relique.co\\src\\lib\\ui\\modules\\partner-strip.tsx", "source_location": "L1"}], "edges": [{"source": "partner_strip", "target": "react", "relation": "imports_from", "confidence": "EXTRACTED", "source_file": "c:\\Users\\minhmice\\Documents\\projects\\relique.co\\src\\lib\\ui\\modules\\partner-strip.tsx", "source_location": "L3", "weight": 1.0}, {"source": "partner_strip", "target": "cn", "relation": "imports_from", "confidence": "EXTRACTED", "source_file": "c:\\Users\\minhmice\\Documents\\projects\\relique.co\\src\\lib\\ui\\modules\\partner-strip.tsx", "source_location": "L4", "weight": 1.0}, {"source": "partner_strip", "target": "bento_grid", "relation": "imports_from", "confidence": "EXTRACTED", "source_file": "c:\\Users\\minhmice\\Documents\\projects\\relique.co\\src\\lib\\ui\\modules\\partner-strip.tsx", "source_location": "L5", "weight": 1.0}, {"source": "partner_strip", "target": "media", "relation": "imports_from", "confidence": "EXTRACTED", "source_file": "c:\\Users\\minhmice\\Documents\\projects\\relique.co\\src\\lib\\ui\\modules\\partner-strip.tsx", "source_location": "L6", "weight": 1.0}]}