{"nodes": [{"id": "firstrunmodal", "label": "FirstRunModal.tsx", "file_type": "code", "source_file": "c:\\Users\\minhmice\\Documents\\projects\\relique.co\\src\\components\\onboarding\\FirstRunModal.tsx", "source_location": "L1"}, {"id": "firstrunmodal_firstrunmodal", "label": "FirstRunModal()", "file_type": "code", "source_file": "c:\\Users\\minhmice\\Documents\\projects\\relique.co\\src\\components\\onboarding\\FirstRunModal.tsx", "source_location": "L16"}], "edges": [{"source": "firstrunmodal", "target": "react", "relation": "imports_from", "confidence": "EXTRACTED", "source_file": "c:\\Users\\minhmice\\Documents\\projects\\relique.co\\src\\components\\onboarding\\FirstRunModal.tsx", "source_location": "L3", "weight": 1.0}, {"source": "firstrunmodal", "target": "dialog", "relation": "imports_from", "confidence": "EXTRACTED", "source_file": "c:\\Users\\minhmice\\Documents\\projects\\relique.co\\src\\components\\onboarding\\FirstRunModal.tsx", "source_location": "L4", "weight": 1.0}, {"source": "firstrunmodal", "target": "button", "relation": "imports_from", "confidence": "EXTRACTED", "source_file": "c:\\Users\\minhmice\\Documents\\projects\\relique.co\\src\\components\\onboarding\\FirstRunModal.tsx", "source_location": "L12", "weight": 1.0}, {"source": "firstrunmodal", "target": "input", "relation": "imports_from", "confidence": "EXTRACTED", "source_file": "c:\\Users\\minhmice\\Documents\\projects\\relique.co\\src\\components\\onboarding\\FirstRunModal.tsx", "source_location": "L13", "weight": 1.0}, {"source": "firstrunmodal", "target": "storage", "relation": "imports_from", "confidence": "EXTRACTED", "source_file": "c:\\Users\\minhmice\\Documents\\projects\\relique.co\\src\\components\\onboarding\\FirstRunModal.tsx", "source_location": "L14", "weight": 1.0}, {"source": "firstrunmodal", "target": "firstrunmodal_firstrunmodal", "relation": "contains", "confidence": "EXTRACTED", "source_file": "c:\\Users\\minhmice\\Documents\\projects\\relique.co\\src\\components\\onboarding\\FirstRunModal.tsx", "source_location": "L16", "weight": 1.0}]}