{"nodes": [{"id": "usemarketplaceitemsview", "label": "useMarketplaceItemsView.ts", "file_type": "code", "source_file": "c:\\Users\\minhmice\\Documents\\projects\\relique.co\\src\\features\\marketplace\\hooks\\useMarketplaceItemsView.ts", "source_location": "L1"}, {"id": "usemarketplaceitemsview_isview", "label": "isView()", "file_type": "code", "source_file": "c:\\Users\\minhmice\\Documents\\projects\\relique.co\\src\\features\\marketplace\\hooks\\useMarketplaceItemsView.ts", "source_location": "L9"}, {"id": "usemarketplaceitemsview_usemarketplaceitemsview", "label": "useMarketplaceItemsView()", "file_type": "code", "source_file": "c:\\Users\\minhmice\\Documents\\projects\\relique.co\\src\\features\\marketplace\\hooks\\useMarketplaceItemsView.ts", "source_location": "L13"}], "edges": [{"source": "usemarketplaceitemsview", "target": "react", "relation": "imports_from", "confidence": "EXTRACTED", "source_file": "c:\\Users\\minhmice\\Documents\\projects\\relique.co\\src\\features\\marketplace\\hooks\\useMarketplaceItemsView.ts", "source_location": "L3", "weight": 1.0}, {"source": "usemarketplaceitemsview", "target": "usemarketplaceitemsview_isview", "relation": "contains", "confidence": "EXTRACTED", "source_file": "c:\\Users\\minhmice\\Documents\\projects\\relique.co\\src\\features\\marketplace\\hooks\\useMarketplaceItemsView.ts", "source_location": "L9", "weight": 1.0}, {"source": "usemarketplaceitemsview", "target": "usemarketplaceitemsview_usemarketplaceitemsview", "relation": "contains", "confidence": "EXTRACTED", "source_file": "c:\\Users\\minhmice\\Documents\\projects\\relique.co\\src\\features\\marketplace\\hooks\\useMarketplaceItemsView.ts", "source_location": "L13", "weight": 1.0}]}